octicons_pack/__init__.py
octicons_pack/__init__.pyi
octicons_pack/octicons_pack.abi3.so
octicons_pack/py.typed
octicons_pack-19.21.2.dist-info/METADATA
octicons_pack-19.21.2.dist-info/WHEEL
octicons_pack-19.21.2.dist-info/licenses/LICENSE
octicons_pack-19.21.2.dist-info/RECORD
