Metadata-Version: 2.4
Name: octicons-pack
Version: 19.21.2
Classifier: Programming Language :: Rust
Classifier: Programming Language :: Python :: Implementation :: CPython
Classifier: Programming Language :: Python :: Implementation :: PyPy
License-File: LICENSE
Summary: A redistribution of @primer/octicons npm package's SVG and metadata.
License: MIT
Requires-Python: >=3.8
Project-URL: source, https://github.com/2bndy5/redist-icons
